tc_release/__init__.py
tc_release/__main__.py
tc_release/_version.py
tc_release/tc_release.py
tc_release/tcgvl.txt
tc_release/version.py
tc_release/tests/__init__.py
tc_release/tests/test_make_release.py
tc_release/tests/artifacts/artifacts.txt
tc_release-0.2.6.dist-info/AUTHORS.rst
tc_release-0.2.6.dist-info/LICENSE
tc_release-0.2.6.dist-info/METADATA
tc_release-0.2.6.dist-info/WHEEL
tc_release-0.2.6.dist-info/entry_points.txt
tc_release-0.2.6.dist-info/top_level.txt
tc_release-0.2.6.dist-info/RECORD
